{"en_plugin_plugin-epub.md":"ZeA7ixG5","en_index.md":"jrSB47Jd","index.md":"7BjSd9wq","book.md":"HMb8ijuo","development.md":"5sE1jX_x","plugin_plugin-docs.md":"7d9Hm0MA","plugin_plugin-hexo.md":"Jivpdu8x","en_development.md":"DUTGIJpY","en_plugin_plugin-docs.md":"HKf9Cyf6","en_book.md":"pJjWTGBX","en_api.md":"DHGNZ_C8","en_plugin_plugin-hexo.md":"7PD5tqlr","plugin_plugin-doctran.md":"_cv9xsfX","plugin_index.md":"LENRtNZU","blog.md":"lEdQeoHi","plugin_plugin-joplin.md":"bce_3Hab","en_plugin_index.md":"i1uB6_AL","api-plugin.md":"tPv0CkPq","config.md":"PeL54KuE","en_config.md":"SECvgy4Y","en_plugin_plugin-doctran.md":"Qw8jIV7e","en_blog.md":"EmrcvxdJ","deploy.md":"Re9ELVpF","plugin_plugin-epub.md":"OBlQeMmy","en_plugin_plugin-local.md":"zASNE3Pk","plugin_plugin-local.md":"4jS2ReX1","en_plugin_plugin-joplin.md":"UVeRKjqs","api.md":"p7tP_k4V","en_api-plugin.md":"-XxIZyN7","en_deploy.md":"nogzBdVq"}
